setup.cfg
setup.py
pypsus1234/__init__.py
pypsus1234/app.py
pypsus1234.egg-info/PKG-INFO
pypsus1234.egg-info/SOURCES.txt
pypsus1234.egg-info/dependency_links.txt
pypsus1234.egg-info/top_level.txt