Metadata-Version: 2.1
Name: pypsus1234
Version: 0.0.1
Summary: Description of your package
Author: Privet-Kotlet
Author-email: ruslanf927@gmail.com
License: MIT
